LICENSE
MANIFEST.in
README.rst
setup.py
bin/makisu
docs/makimono-enricher-example.ipynb
docs/makimono-plotter-examples.ipynb
makimono/__init__.py
makimono/data.json
makimono/enricher.py
makimono/plotter.py
makimono/templater.py
makimono/toolbox.py
makimono.egg-info/PKG-INFO
makimono.egg-info/SOURCES.txt
makimono.egg-info/dependency_links.txt
makimono.egg-info/not-zip-safe
makimono.egg-info/requires.txt
makimono.egg-info/top_level.txt