Metadata-Version: 1.1
Name: makimono
Version: 0.1.4
Summary: Visualizations for RNA-Seq expression data
Home-page: http://github.com/hpsbastos/makimono
Author: hpbastos
Author-email: hpb29@cam.ac.uk
License: MIT
Keywords: makimono RNA-Seq visualization
Platform: UNKNOWN
Classifier: Development Status :: 3 - Alpha
Classifier: License :: OSI Approved :: MIT License
Classifier: Programming Language :: Python :: 2.7
Classifier: Operating System :: POSIX :: Linux
Classifier: Topic :: Scientific/Engineering :: Bio-Informatics
